pepperize_cdk_lambda_deno/__init__.py
pepperize_cdk_lambda_deno/py.typed
pepperize_cdk_lambda_deno/_jsii/__init__.py
pepperize_cdk_lambda_deno/_jsii/cdk-lambda-deno@0.0.580.jsii.tgz
pepperize_cdk_lambda_deno-0.0.580.dist-info/LICENSE
pepperize_cdk_lambda_deno-0.0.580.dist-info/METADATA
pepperize_cdk_lambda_deno-0.0.580.dist-info/WHEEL
pepperize_cdk_lambda_deno-0.0.580.dist-info/top_level.txt
pepperize_cdk_lambda_deno-0.0.580.dist-info/RECORD
